binance/__init__.py
binance/cmfutures/__init__.py
binance/cmfutures/api_client.py
binance/cmfutures/api_response.py
binance/cmfutures/configuration.py
binance/cmfutures/exceptions.py
binance/cmfutures/rest.py
binance/cmfutures/signing.py
binance/cmfutures/api/__init__.py
binance/cmfutures/api/futures_api.py
binance/cmfutures/models/__init__.py
binance/cmfutures/models/api_error.py
binance/cmfutures/models/cmfutures_create_batch_order_v1_req_batch_orders_item.py
binance/cmfutures/models/cmfutures_create_batch_orders_v1_resp_inner.py
binance/cmfutures/models/cmfutures_create_batch_orders_v1_resp_item.py
binance/cmfutures/models/cmfutures_delete_batch_orders_v1_resp_inner.py
binance/cmfutures/models/cmfutures_delete_batch_orders_v1_resp_item.py
binance/cmfutures/models/cmfutures_get_continuous_klines_v1_resp_inner_inner.py
binance/cmfutures/models/cmfutures_get_exchange_info_v1_resp.py
binance/cmfutures/models/cmfutures_get_exchange_info_v1_resp_rate_limits_inner.py
binance/cmfutures/models/cmfutures_get_exchange_info_v1_resp_symbols_inner.py
binance/cmfutures/models/cmfutures_get_force_orders_v1_resp_item.py
binance/cmfutures/models/cmfutures_symbol_filter.py
binance/cmfutures/models/cmfutures_update_batch_orders_v1_req_batch_orders_item.py
binance/cmfutures/models/cmfutures_update_batch_orders_v1_resp_inner.py
binance/cmfutures/models/cmfutures_update_batch_orders_v1_resp_item.py
binance/cmfutures/models/create_countdown_cancel_all_v1_resp.py
binance/cmfutures/models/create_leverage_v1_resp.py
binance/cmfutures/models/create_listen_key_v1_resp.py
binance/cmfutures/models/create_margin_type_v1_resp.py
binance/cmfutures/models/create_order_v1_resp.py
binance/cmfutures/models/create_position_margin_v1_resp.py
binance/cmfutures/models/create_position_side_dual_v1_resp.py
binance/cmfutures/models/delete_all_open_orders_v1_resp.py
binance/cmfutures/models/delete_order_v1_resp.py
binance/cmfutures/models/get_account_v1_resp.py
openxapi_binance-0.3.0.dist-info/licenses/LICENSE
openxapi_binance-0.3.0.dist-info/METADATA
openxapi_binance-0.3.0.dist-info/WHEEL
openxapi_binance-0.3.0.dist-info/top_level.txt
openxapi_binance-0.3.0.dist-info/RECORD
