Metadata-Version: 2.4
Name: openxapi-binance
Version: 0.3.0
Summary: Python client for Binance API
Home-page: https://github.com/openxapi/binance-py
Author: OpenXAPI
Author-email: contact@openxapi.com
License: MIT
Keywords: OpenXAPI,OpenAPI,binance,binance-python
License-File: LICENSE
Requires-Dist: urllib3<3.0.0,>=1.25.3
Requires-Dist: python_dateutil>=2.8.2
Requires-Dist: pycryptodome>=3.9.0
Requires-Dist: pydantic>=2
Requires-Dist: typing-extensions>=4.7.1
Dynamic: author
Dynamic: author-email
Dynamic: description
Dynamic: description-content-type
Dynamic: home-page
Dynamic: keywords
Dynamic: license
Dynamic: license-file
Dynamic: requires-dist
Dynamic: summary
